src/__init__.py
src/analysis/__init__.py
src/analysis/argument.py
src/analysis/config.py
src/analysis/result.py
src/analysis/runner.py
src/checkers/__init__.py
src/checkers/base_checker.py
src/checkers/checker_4_11_hyperparameter_not_explicitly_set.py
src/checkers/checker_4_13_deterministic_algorithm_option_not_used.py
src/checkers/checker_4_14_randomness_uncontrolled.py
src/checkers/checker_4_15_missing_the_mask_of_invalid_value.py
src/checkers/checker_4_17_tensorarray_not_used.py
src/checkers/checker_4_19_pytorch_call_method_misused.py
src/checkers/checker_4_2_nan_equivalence_comparison_misused.py
src/checkers/checker_4_3_chain_indexing.py
src/checkers/checker_4_4_columns_and_data_type_not_explicitly_set.py
src/checkers/checker_4_5_empty_column_misinitialization.py
src/checkers/checker_4_6_merge_api_parameter_not_explicitly_set.py
src/checkers/checker_4_7_in_place_apis_misused.py
src/checkers/checker_4_8_dataframe_conversion_api_misused.py
src/checkers/checker_4_9_matrix_multiplication_api_misused.py
src/checkers/advice/__init__.py
src/checkers/advice/advice_checker_4_12_memory_not_freed.py
src/checkers/advice/advice_checker_4_16_broadcasting_feature_not_used.py
src/checkers/advice/advice_checker_4_18_training_evaluation_mode_improper_toggling.py
src/checkers/advice/advice_checker_4_1_unnecessary_iteration.py
src/checkers/advice/advice_checker_4_20_gradients_not_cleared_before_backward_propagation.py
src/checkers/advice/advice_checker_4_21_data_leakage.py
tests/__init__.py
tests/test_utils.py
tests/test_checkers/__init__.py
tests/test_checkers/test_advice_checker_4_12_memory_not_freed.py
tests/test_checkers/test_advice_checker_4_16_broadcasting_feature_not_used.py
tests/test_checkers/test_advice_checker_4_18_training_evaluation_mode_improper_toggling.py
tests/test_checkers/test_advice_checker_4_1_unnecessary_iteration.py
tests/test_checkers/test_advice_checker_4_20_gradients_not_cleared_before_backward_propagation.py
mlpylint-0.0.3.dist-info/LICENSE
mlpylint-0.0.3.dist-info/METADATA
mlpylint-0.0.3.dist-info/WHEEL
mlpylint-0.0.3.dist-info/entry_points.txt
mlpylint-0.0.3.dist-info/top_level.txt
mlpylint-0.0.3.dist-info/RECORD
