Metadata-Version: 2.1
Name: mlpylint
Version: 0.0.3
Summary: MLpylint, a static analysis tool for identifying ML-specific code smells
Author: Peter Hamfelt
Author-email: peter.hamfelt@gmail.com
Keywords: linting,static-analysis,python-linting,python-static-analysis,machine-learning,machine-learning-engineering,ML-model-quality,artificial-intelligence,python,software-quality,technical-debt,software-engineering,maintainability,code-smell
Classifier: Development Status :: 4 - Beta
Classifier: Environment :: Console
Classifier: Intended Audience :: Developers
Classifier: License :: OSI Approved :: MIT License
Classifier: Operating System :: OS Independent
Classifier: Programming Language :: Python :: 3
Classifier: Programming Language :: Python :: 3.6
Classifier: Programming Language :: Python :: 3.7
Classifier: Programming Language :: Python :: 3.8
Classifier: Programming Language :: Python :: 3.9
Classifier: Programming Language :: Python :: 3.10
Classifier: Topic :: Software Development :: Quality Assurance
Classifier: Topic :: Software Development :: Libraries :: Python Modules
Classifier: Topic :: Software Development :: Testing
Classifier: Topic :: Scientific/Engineering :: Artificial Intelligence
License-File: LICENSE
Requires-Dist: astroid (>=2.15.1)
Requires-Dist: colorama
Requires-Dist: tensorflow
Requires-Dist: pandas
Requires-Dist: numpy
Requires-Dist: scikit-learn
Requires-Dist: torch
Provides-Extra: dev
Requires-Dist: pytest (>=7.2.2) ; extra == 'dev'
